CHANGES.rst
CONTRIBUTORS.rst
LICENSE
MANIFEST.in
README.rst
setup.py
bin/edeposit_amqp_aleph_link_exportd.py
bin/edeposit_amqp_alephdaemon.py
bin/edeposit_amqp_antivirusd.py
bin/edeposit_amqp_calibredaemon.py
bin/edeposit_amqp_downloaderd.py
bin/edeposit_amqp_ftp_managerd.py
bin/edeposit_amqp_ftp_monitord.py
bin/edeposit_amqp_harvester.py
bin/edeposit_amqp_ltpd.py
bin/edeposit_amqp_marcxml2modsd.py
bin/edeposit_amqp_pdfgend.py
bin/edeposit_amqp_storaged.py
bin/edeposit_amqp_tool.py
docs/Makefile
docs/__init__.py
docs/conf.py
docs/index.rst
docs/requirements.txt
docs/update_templates.sh
docs/_static/communication.png
docs/_static/communication.uml.txt
docs/_static/structure.png
docs/_static/structure.uml
docs/_static/template_structure.uml
docs/api/aleph_link_exportd.rst
docs/api/downloaderd.rst
docs/api/edeposit.amqp.alephdaemon.rst
docs/api/edeposit.amqp.amqpdaemon.rst
docs/api/edeposit.amqp.antivirus.rst
docs/api/edeposit.amqp.calibredaemon.rst
docs/api/edeposit.amqp.daemonwrapper.rst
docs/api/edeposit.amqp.pikadaemon.rst
docs/api/edeposit.amqp.rst
docs/api/edeposit.amqp.settings.rst
docs/api/edeposit.amqp.tool.rst
docs/api/ftp_managerd.rst
docs/api/ftp_monitord.rst
docs/api/harvester.rst
docs/api/ltpd.rst
docs/api/marcxml2modsd.rst
docs/api/pdfgend.rst
docs/api/storaged.rst
edeposit/__init__.py
edeposit.amqp.egg-info/PKG-INFO
edeposit.amqp.egg-info/SOURCES.txt
edeposit.amqp.egg-info/dependency_links.txt
edeposit.amqp.egg-info/namespace_packages.txt
edeposit.amqp.egg-info/not-zip-safe
edeposit.amqp.egg-info/requires.txt
edeposit.amqp.egg-info/top_level.txt
edeposit/amqp/__init__.py
edeposit/amqp/amqpdaemon.py
edeposit/amqp/daemonwrapper.py
edeposit/amqp/pikadaemon.py
edeposit/amqp/settings.py
edeposit/amqp/tests/integration/test_aleph.py
edeposit/amqp/tests/integration/test_daemons.py
edeposit/amqp/tests/integration/test_package.py
edeposit/amqp/tests/unittests/test_settings.py