Metadata-Version: 1.1
Name: edeposit.amqp
Version: 1.8.13
Summary: E-Deposit's AMQP definitions and common classes/patterns.
Home-page: https://github.com/edeposit/edeposit.amqp/
Author: Edeposit team
Author-email: edeposit@email.cz
License: GPL2+
Platform: UNKNOWN
Classifier: Intended Audience :: Developers
Classifier: Programming Language :: Python :: 2
Classifier: Programming Language :: Python :: 2.7
Classifier: License :: OSI Approved :: MIT License
Classifier: Topic :: Software Development :: Libraries :: Python Modules
